rivendellaudio/__init__.py
rivendellaudio/pypad.py
rivendellaudio/rivwebpyapi.py
rivendellaudio-4.2.2.dist-info/LICENSE
rivendellaudio-4.2.2.dist-info/METADATA
rivendellaudio-4.2.2.dist-info/WHEEL
rivendellaudio-4.2.2.dist-info/top_level.txt
rivendellaudio-4.2.2.dist-info/RECORD
