Metadata-Version: 2.1
Name: rivendellaudio
Version: 4.2.2
Summary: Python 3 interface to the Rivendell Radio Automation System
Home-page: https://github.com/ElvishArtisan/rivendell
Author: Fred Gleason
Author-email: fredg@paravelsystems.com
Project-URL: Bug Tracker, https://github.com/ElvishArtisan/rivendell/issues
Classifier: Programming Language :: Python :: 3
Classifier: License :: OSI Approved :: GNU Lesser General Public License v2 (LGPLv2)
Classifier: Operating System :: OS Independent
Requires-Python: >=3.6
License-File: LICENSE
Requires-Dist: mysqlclient >=1.3.12
Requires-Dist: requests >=2.14.2
